blendpy/__init__.py
blendpy/_version.py
blendpy/alloy.py
blendpy/constants.py
blendpy/dsi_model.py
blendpy/intermetallics.py
blendpy/local_order.py
blendpy/phase_diagram.py
blendpy/old_proposal/polymorph.py
blendpy-25.11.0.dist-info/METADATA
blendpy-25.11.0.dist-info/WHEEL
blendpy-25.11.0.dist-info/licenses/LICENSE
blendpy-25.11.0.dist-info/RECORD
