Metadata-Version: 2.4
Name: blendpy
Version: 25.11.0
Summary: Blendpy is a computational toolkit for investigating thermodynamic models of alloys using first-principles calculations.
Project-URL: Homepage, https://github.com/leseixas/blendpy
Project-URL: Repository, https://github.com/leseixas/blendpy
Author-email: Leandro Seixas <leandro.seixas@proton.me>
License: MIT License
License-File: LICENSE
Classifier: License :: OSI Approved :: MIT License
Classifier: Operating System :: OS Independent
Classifier: Programming Language :: Python :: 3
Classifier: Topic :: Scientific/Engineering :: Chemistry
Classifier: Topic :: Scientific/Engineering :: Physics
Requires-Python: >=3.8
Requires-Dist: ase
Requires-Dist: mpltern
Requires-Dist: numpy
Requires-Dist: pandas
Requires-Dist: pytest
Requires-Dist: pyyaml
Requires-Dist: tqdm
